tldparse/__init__.py
tldparse/__version__.py
tldparse/public_suffix_list.dat
tldparse/tests.py
tldparse-1.0.5.dist-info/LICENSE
tldparse-1.0.5.dist-info/METADATA
tldparse-1.0.5.dist-info/WHEEL
tldparse-1.0.5.dist-info/top_level.txt
tldparse-1.0.5.dist-info/RECORD
