Metadata-Version: 2.1
Name: tldparse
Version: 1.0.5
Summary: Parse a given domain and split it into its subdomain, domain and top-level domain parts.
Home-page: https://github.com/cnicodeme/tldparse
Author: Cyril Nicodeme
Author-email: contact@cnicodeme.com
License: MIT
Project-URL: Source, https://github.com/cnicodeme/tldparse
Keywords: domain parser tld top-level domain subdomain
Platform: any
Classifier: Development Status :: 5 - Production/Stable
Classifier: Intended Audience :: Developers
Classifier: Topic :: Internet
Classifier: Topic :: Internet :: Name Service (DNS)
Classifier: Topic :: Internet :: WWW/HTTP
Classifier: Topic :: System :: Networking
Classifier: License :: OSI Approved :: MIT License
Classifier: Operating System :: OS Independent
Classifier: Programming Language :: Python
Classifier: Programming Language :: Python :: 3
Classifier: Programming Language :: Python :: 3.3
Classifier: Programming Language :: Python :: 3.4
Classifier: Programming Language :: Python :: 3.5
Classifier: Programming Language :: Python :: 3.6
Classifier: Programming Language :: Python :: 3.7
Classifier: Programming Language :: Python :: 3.8
Classifier: Programming Language :: Python :: 3.9
Classifier: Programming Language :: Python :: 3.10
Classifier: Programming Language :: Python :: Implementation :: PyPy
License-File: LICENSE
